__init__.py
app.py
lib/__init__.py
lib/rename.py
lib/resize.py
tests/__init__.py
tests/conftest.py
tests/test_lib/__init__.py
tests/test_lib/test_rename.py
tests/test_utils/__init__.py
tests/test_utils/test_exception.py
tests/test_utils/test_stdout.py
tests/test_utils/test_utils.py
utils/__init__.py
utils/constants.py
utils/exception.py
utils/rename.py
utils/stdout.py
utils/tests.py
utils/with_statements.py
image_pyconverter_cli-1.1.0.dist-info/LICENCE
image_pyconverter_cli-1.1.0.dist-info/METADATA
image_pyconverter_cli-1.1.0.dist-info/WHEEL
image_pyconverter_cli-1.1.0.dist-info/entry_points.txt
image_pyconverter_cli-1.1.0.dist-info/top_level.txt
image_pyconverter_cli-1.1.0.dist-info/RECORD
