Metadata-Version: 2.1
Name: image-pyconverter-cli
Version: 1.1.0
Summary: Image Conversion Tools.
Home-page: https://github.com/ShuntaH/image_pyconverter_cli
Author: ShuntaH
Author-email: hskpg.contact@gmail.com
License: MIT License
Keywords: Image converter,Rename,Python,CLI
Platform: POSIX
Platform: Windows
Platform: Unix
Platform: MacOS
Classifier: Intended Audience :: Developers
Classifier: Topic :: Software Development :: Libraries :: Python Modules
Classifier: License :: OSI Approved :: MIT License
Classifier: Programming Language :: Python :: 3.8
Classifier: Programming Language :: Python :: 3.9
Classifier: Programming Language :: Python :: 3.10
Classifier: Programming Language :: Python :: 3.11
Classifier: Operating System :: OS Independent
Classifier: Operating System :: POSIX
Classifier: Operating System :: Microsoft
Classifier: Operating System :: MacOS
Classifier: Operating System :: Unix
License-File: LICENCE
Requires-Dist: Pillow
Requires-Dist: jaconv
Requires-Dist: python-dotenv
